next_gen_ui_langgraph/__init__.py
next_gen_ui_langgraph/agent.py
next_gen_ui_langgraph/agent_dev.py
next_gen_ui_langgraph/readme_example.py
next_gen_ui_langgraph-0.3.0.dist-info/METADATA
next_gen_ui_langgraph-0.3.0.dist-info/WHEEL
next_gen_ui_langgraph-0.3.0.dist-info/namespace_packages.txt
next_gen_ui_langgraph-0.3.0.dist-info/top_level.txt
next_gen_ui_langgraph-0.3.0.dist-info/RECORD
