Metadata-Version: 2.1
Name: next_gen_ui_langgraph
Version: 0.3.0
Summary: LangGraph integration for Next Gen UI Agent
Home-page: https://github.com/RedHat-UX/next-gen-ui-agent
License: Apache-2.0
Classifier: Programming Language :: Python :: 3
Classifier: Programming Language :: Python :: 3.12
Classifier: Programming Language :: Python :: 3.13
Classifier: License :: OSI Approved :: Apache Software License
Requires-Python: <3.14,>=3.12
Requires-Dist: langchain-core<=0.3.66
Requires-Dist: langchain-openai<=0.3.25
Requires-Dist: langgraph<=0.3.34
Requires-Dist: next-gen-ui-agent==0.3.0
Requires-Dist: typing-extensions
